nlp_synt_data/__init__.py
nlp_synt_data/generator.py
nlp_synt_data-0.0.11.dist-info/LICENSE
nlp_synt_data-0.0.11.dist-info/METADATA
nlp_synt_data-0.0.11.dist-info/WHEEL
nlp_synt_data-0.0.11.dist-info/top_level.txt
nlp_synt_data-0.0.11.dist-info/RECORD
