Metadata-Version: 2.1
Name: nlp_synt_data
Version: 0.0.11
Summary: Synthesized Data for NLP Tasks
Home-page: https://github.com/tommasoromano/nlp-synt-data
Author: Tommaso Romano'
Author-email: romabob1300@gmail.com
License: The MIT License (MIT)
Classifier: Programming Language :: Python :: 3
Classifier: License :: OSI Approved :: MIT License
Classifier: Operating System :: OS Independent
License-File: LICENSE
Requires-Dist: pandas
